{
  "version": "2.4.1",
  "summary": {
    "title": "Threat model",
    "owner": "FTN projekti",
    "description": "",
    "id": 0
  },
  "detail": {
    "contributors": [
      {
        "name": "Maša Ivanov"
      },
      {
        "name": "Milan Arežina"
      },
      {
        "name": "Dimitrije Gašić"
      }
    ],
    "diagrams": [
      {
        "id": 0,
        "title": "DFD diagram",
        "diagramType": "STRIDE",
        "placeholder": "New STRIDE diagram description",
        "thumbnail": "./public/content/images/thumbnail.stride.jpg",
        "version": "2.4.1",
        "cells": [
          {
            "angle": 150,
            "position": {
              "x": 120,
              "y": -640
            },
            "size": {
              "width": 720,
              "height": 500
            },
            "visible": true,
            "shape": "trust-boundary-box",
            "id": "d3b12d59-ec29-4697-b563-250312e70a1d",
            "zIndex": -1,
            "data": {
              "type": "tm.BoundaryBox",
              "name": "Trust Boundary",
              "description": "",
              "isTrustBoundary": true,
              "hasOpenThreats": false
            }
          },
          {
            "position": {
              "x": 480,
              "y": 270
            },
            "size": {
              "width": 112.5,
              "height": 60
            },
            "attrs": {
              "body": {
                "stroke": "red",
                "strokeWidth": 2.5,
                "strokeDasharray": null
              }
            },
            "visible": true,
            "shape": "actor",
            "zIndex": 1,
            "ports": {
              "groups": {
                "top": {
                  "position": "top",
                  "attrs": {
                    "circle": {
                      "r": 4,
                      "magnet": true,
                      "stroke": "#5F95FF",
                      "strokeWidth": 1,
                      "fill": "#fff",
                      "style": {
                        "visibility": "hidden"
                      }
                    }
                  }
                },
                "right": {
                  "position": "right",
                  "attrs": {
                    "circle": {
                      "r": 4,
                      "magnet": true,
                      "stroke": "#5F95FF",
                      "strokeWidth": 1,
                      "fill": "#fff",
                      "style": {
                        "visibility": "hidden"
                      }
                    }
                  }
                },
                "bottom": {
                  "position": "bottom",
                  "attrs": {
                    "circle": {
                      "r": 4,
                      "magnet": true,
                      "stroke": "#5F95FF",
                      "strokeWidth": 1,
                      "fill": "#fff",
                      "style": {
                        "visibility": "hidden"
                      }
                    }
                  }
                },
                "left": {
                  "position": "left",
                  "attrs": {
                    "circle": {
                      "r": 4,
                      "magnet": true,
                      "stroke": "#5F95FF",
                      "strokeWidth": 1,
                      "fill": "#fff",
                      "style": {
                        "visibility": "hidden"
                      }
                    }
                  }
                }
              },
              "items": [
                {
                  "group": "top",
                  "id": "506c9cc6-f584-4303-bf06-ce2f1109509b"
                },
                {
                  "group": "right",
                  "id": "e8a1efcc-d9c1-47da-8cfe-f96090c558d5"
                },
                {
                  "group": "bottom",
                  "id": "1931cf53-c568-44fc-a98c-6e997079a10e"
                },
                {
                  "group": "left",
                  "id": "61830ef7-b9b2-4e68-aca6-c994d048f964"
                }
              ]
            },
            "id": "53a30cbd-7c82-49d0-a6df-5b77c9a7abd7",
            "data": {
              "type": "tm.Actor",
              "name": "Actor",
              "description": "",
              "isTrustBoundary": false,
              "outOfScope": false,
              "reasonOutOfScope": "",
              "hasOpenThreats": true,
              "providesAuthentication": false,
              "threats": [
                {
                  "id": "5007c050-9e24-4179-91d4-c54bfc3c4769",
                  "title": "New STRIDE threat",
                  "status": "Open",
                  "severity": "TBD",
                  "type": "Spoofing",
                  "description": "Provide a description for this threat",
                  "mitigation": "Provide remediation for this threat or a reason if status is N/A",
                  "modelType": "STRIDE",
                  "new": false,
                  "number": 1,
                  "score": ""
                },
                {
                  "id": "dfdf4b37-2a65-46ce-a41f-d75dc44ffbd9",
                  "title": "New STRIDE threat",
                  "status": "Open",
                  "severity": "TBD",
                  "type": "Repudiation",
                  "description": "Provide a description for this threat",
                  "mitigation": "Provide remediation for this threat or a reason if status is N/A",
                  "modelType": "STRIDE",
                  "new": false,
                  "number": 2,
                  "score": ""
                }
              ],
              "threatFrequency": {
                "spoofing": 1,
                "repudiation": 1
              }
            }
          },
          {
            "position": {
              "x": 720,
              "y": 240
            },
            "size": {
              "width": 60,
              "height": 60
            },
            "attrs": {
              "body": {
                "stroke": "#333333",
                "strokeWidth": 1.5,
                "strokeDasharray": null
              }
            },
            "visible": true,
            "shape": "process",
            "zIndex": 2,
            "ports": {
              "groups": {
                "top": {
                  "position": "top",
                  "attrs": {
                    "circle": {
                      "r": 4,
                      "magnet": true,
                      "stroke": "#5F95FF",
                      "strokeWidth": 1,
                      "fill": "#fff",
                      "style": {
                        "visibility": "hidden"
                      }
                    }
                  }
                },
                "right": {
                  "position": "right",
                  "attrs": {
                    "circle": {
                      "r": 4,
                      "magnet": true,
                      "stroke": "#5F95FF",
                      "strokeWidth": 1,
                      "fill": "#fff",
                      "style": {
                        "visibility": "hidden"
                      }
                    }
                  }
                },
                "bottom": {
                  "position": "bottom",
                  "attrs": {
                    "circle": {
                      "r": 4,
                      "magnet": true,
                      "stroke": "#5F95FF",
                      "strokeWidth": 1,
                      "fill": "#fff",
                      "style": {
                        "visibility": "hidden"
                      }
                    }
                  }
                },
                "left": {
                  "position": "left",
                  "attrs": {
                    "circle": {
                      "r": 4,
                      "magnet": true,
                      "stroke": "#5F95FF",
                      "strokeWidth": 1,
                      "fill": "#fff",
                      "style": {
                        "visibility": "hidden"
                      }
                    }
                  }
                }
              },
              "items": [
                {
                  "group": "top",
                  "id": "717368e1-f0d9-49ac-994d-ffa3ad10c27c"
                },
                {
                  "group": "right",
                  "id": "032759b6-f1ef-48b2-9a0f-219774a40cc6"
                },
                {
                  "group": "bottom",
                  "id": "380d566b-dbd4-4511-a000-65db17df2296"
                },
                {
                  "group": "left",
                  "id": "b61fe709-fa3a-411d-9d4b-4dbdffd1bb74"
                }
              ]
            },
            "id": "bc222ac2-d59c-4cd4-bdad-60b52c60ad82",
            "data": {
              "type": "tm.Process",
              "name": "Process",
              "description": "",
              "outOfScope": false,
              "isTrustBoundary": false,
              "reasonOutOfScope": "",
              "hasOpenThreats": false,
              "handlesCardPayment": false,
              "handlesGoodsOrServices": false,
              "isWebApplication": false,
              "privilegeLevel": "",
              "threats": []
            }
          },
          {
            "shape": "flow",
            "attrs": {
              "line": {
                "stroke": "#333333",
                "targetMarker": {
                  "name": "block"
                },
                "sourceMarker": {
                  "name": ""
                },
                "strokeDasharray": null
              }
            },
            "width": 200,
            "height": 100,
            "zIndex": 10,
            "connector": "smooth",
            "data": {
              "type": "tm.Flow",
              "name": "Data Flow",
              "description": "",
              "outOfScope": false,
              "isTrustBoundary": false,
              "reasonOutOfScope": "",
              "hasOpenThreats": false,
              "isBidirectional": false,
              "isEncrypted": false,
              "isPublicNetwork": false,
              "protocol": "",
              "threats": []
            },
            "labels": [
              "Data Flow"
            ],
            "id": "db743787-bc51-4921-b279-8b5a110b1352",
            "source": {
              "x": 500,
              "y": 430
            },
            "target": {
              "x": 600,
              "y": 530
            }
          },
          {
            "position": {
              "x": 1080,
              "y": 270
            },
            "size": {
              "width": 120,
              "height": 60
            },
            "attrs": {
              "topLine": {
                "strokeWidth": 1.5,
                "strokeDasharray": null
              },
              "bottomLine": {
                "strokeWidth": 1.5,
                "strokeDasharray": null
              }
            },
            "visible": true,
            "shape": "store",
            "ports": {
              "groups": {
                "top": {
                  "position": "top",
                  "attrs": {
                    "circle": {
                      "r": 4,
                      "magnet": true,
                      "stroke": "#5F95FF",
                      "strokeWidth": 1,
                      "fill": "#fff",
                      "style": {
                        "visibility": "hidden"
                      }
                    }
                  }
                },
                "right": {
                  "position": "right",
                  "attrs": {
                    "circle": {
                      "r": 4,
                      "magnet": true,
                      "stroke": "#5F95FF",
                      "strokeWidth": 1,
                      "fill": "#fff",
                      "style": {
                        "visibility": "hidden"
                      }
                    }
                  }
                },
                "bottom": {
                  "position": "bottom",
                  "attrs": {
                    "circle": {
                      "r": 4,
                      "magnet": true,
                      "stroke": "#5F95FF",
                      "strokeWidth": 1,
                      "fill": "#fff",
                      "style": {
                        "visibility": "hidden"
                      }
                    }
                  }
                },
                "left": {
                  "position": "left",
                  "attrs": {
                    "circle": {
                      "r": 4,
                      "magnet": true,
                      "stroke": "#5F95FF",
                      "strokeWidth": 1,
                      "fill": "#fff",
                      "style": {
                        "visibility": "hidden"
                      }
                    }
                  }
                }
              },
              "items": [
                {
                  "group": "top",
                  "id": "1121d765-9169-4ec0-8e35-291120c7386e"
                },
                {
                  "group": "right",
                  "id": "469ceef8-c8b3-4b6b-96eb-4fbe135c3f94"
                },
                {
                  "group": "bottom",
                  "id": "3768b04b-03b8-4602-9c83-96edc1fa39c2"
                },
                {
                  "group": "left",
                  "id": "4c6fd401-b88f-4e96-a6d0-ae23270abae6"
                }
              ]
            },
            "id": "6d704d07-8ef0-4a22-8352-f6e0a0f33fc1",
            "zIndex": 11,
            "data": {
              "type": "tm.Store",
              "name": "Store",
              "description": "",
              "outOfScope": false,
              "isTrustBoundary": false,
              "reasonOutOfScope": "",
              "hasOpenThreats": false,
              "isALog": false,
              "isEncrypted": false,
              "isSigned": false,
              "storesCredentials": false,
              "storesInventory": false,
              "threats": []
            }
          }
        ]
      }
    ],
    "diagramTop": 1,
    "reviewer": "",
    "threatTop": 2
  }
}